fairensics/__init__.py
fairensics/fairensics_utils.py
fairensics/data/__init__.py
fairensics/data/decision_boundary.py
fairensics/data/synthetic_dataset.py
fairensics/methods/__init__.py
fairensics/methods/disparate_impact.py
fairensics/methods/disparate_mistreatment.py
fairensics/methods/fairness_warnings.py
fairensics/methods/preferential_fairness.py
fairensics/methods/utils.py
fairensics-0.0.2.dist-info/LICENSE
fairensics-0.0.2.dist-info/METADATA
fairensics-0.0.2.dist-info/WHEEL
fairensics-0.0.2.dist-info/top_level.txt
fairensics-0.0.2.dist-info/RECORD
